mdbook_pdf_summary/__init__.py
mdbook_pdf_summary/check_title.py
mdbook_pdf_summary/mdbook_pdf_summary.py
mdbook_pdf_summary/parse_section.py
mdbook_pdf_summary-0.1.1.dist-info/METADATA
mdbook_pdf_summary-0.1.1.dist-info/WHEEL
mdbook_pdf_summary-0.1.1.dist-info/entry_points.txt
mdbook_pdf_summary-0.1.1.dist-info/top_level.txt
mdbook_pdf_summary-0.1.1.dist-info/RECORD
