Metadata-Version: 2.1
Name: mdbook_pdf_summary
Version: 0.1.1
Summary: Generate outline for pdf generated by `mdbook-pdf`.
Author: cmq2525
Author-email: cmq2525@foxmail.com
Classifier: Programming Language :: Python :: 3
Classifier: License :: OSI Approved :: MIT License
Classifier: Operating System :: OS Independent
Requires-Dist: lxml ==5.2.1
Requires-Dist: pypdf ==4.2.0
